pwb_toolbox/__init__.py
pwb_toolbox/backtesting/__init__.py
pwb_toolbox/backtesting/backtest_engine.py
pwb_toolbox/backtesting/base_strategy.py
pwb_toolbox/backtesting/commission.py
pwb_toolbox/backtesting/indicators.py
pwb_toolbox/backtesting/optimization_engine.py
pwb_toolbox/backtesting/portfolio.py
pwb_toolbox/backtesting/strategies.py
pwb_toolbox/backtesting/universe.py
pwb_toolbox/datasets/__init__.py
pwb_toolbox/execution/__init__.py
pwb_toolbox/execution/broker_factory.py
pwb_toolbox/execution/ccxt_connector.py
pwb_toolbox/execution/ib_connector.py
pwb_toolbox/execution/live_utils.py
pwb_toolbox/execution/optimal_limit_order.py
pwb_toolbox/performance/__init__.py
pwb_toolbox/performance/metrics.py
pwb_toolbox/performance/nav_metrics.py
pwb_toolbox/performance/plots.py
pwb_toolbox/performance/reports.py
pwb_toolbox/performance/trade_stats.py
pwb_toolbox-0.1.26.dist-info/licenses/LICENSE.txt
pwb_toolbox-0.1.26.dist-info/METADATA
pwb_toolbox-0.1.26.dist-info/WHEEL
pwb_toolbox-0.1.26.dist-info/top_level.txt
pwb_toolbox-0.1.26.dist-info/RECORD
