Metadata-Version: 2.4
Name: pwb-toolbox
Version: 0.1.26
Summary: A toolbox library for quant traders
Home-page: https://github.com/paperswithbacktest/pwb-toolbox
Author: Your Name
Author-email: hello@paperswithbacktest.com
License: MIT
Classifier: Programming Language :: Python :: 3
Classifier: Programming Language :: Python :: 3.10
Classifier: Programming Language :: Python :: 3.11
Classifier: License :: OSI Approved :: MIT License
Classifier: Operating System :: OS Independent
Requires-Python: >=3.10
License-File: LICENSE.txt
Requires-Dist: backtrader
Requires-Dist: beautifulsoup4
Requires-Dist: ccxt
Requires-Dist: click
Requires-Dist: datasets
Requires-Dist: deap
Requires-Dist: ffn
Requires-Dist: huggingface_hub
Requires-Dist: ib_insync
Requires-Dist: matplotlib
Requires-Dist: numpy
Requires-Dist: pandas
Requires-Dist: python-dateutil
Requires-Dist: requests
Requires-Dist: scikit-learn
Requires-Dist: scipy
Requires-Dist: tqdm
Requires-Dist: transformers
Requires-Dist: webdriver_manager
Dynamic: license-file
